LICENSE
README.md
chialisp_loader.py
pyproject.toml
setup.py
chialisp_loader.egg-info/PKG-INFO
chialisp_loader.egg-info/SOURCES.txt
chialisp_loader.egg-info/dependency_links.txt
chialisp_loader.egg-info/requires.txt
chialisp_loader.egg-info/top_level.txt